LICENSE
MANIFEST.in
README.md
requirements.txt
requirements_wsgi.txt
setup.cfg
setup.py
metadataproxy/__init__.py
metadataproxy/roles.py
metadataproxy/settings.py
metadataproxy.egg-info/PKG-INFO
metadataproxy.egg-info/SOURCES.txt
metadataproxy.egg-info/dependency_links.txt
metadataproxy.egg-info/not-zip-safe
metadataproxy.egg-info/requires.txt
metadataproxy.egg-info/top_level.txt
metadataproxy/routes/__init__.py
metadataproxy/routes/mock.py
metadataproxy/routes/proxy.py